LICENSE.md
gnista_cli/__init__.py
gnista_cli/__main__.py
gnista_cli/main.py
gnista_cli/proto_handler.py
gnista_cli/visplore_import.py
gnista_cli-0.1.4.dist-info/LICENSE.md
gnista_cli-0.1.4.dist-info/WHEEL
gnista_cli-0.1.4.dist-info/METADATA
gnista_cli-0.1.4.dist-info/RECORD
