Metadata-Version: 2.1
Name: gnista-cli
Version: 0.1.4
Summary: A CLI client to access gnista.io
Home-page: https://gnista.io
License: MIT
Author: Markus Hoffmann
Requires-Python: >=3.9,<4.0
Classifier: License :: OSI Approved :: MIT License
Classifier: Programming Language :: Python :: 3
Classifier: Programming Language :: Python :: 3.9
Requires-Dist: argparse (>=1.4.0,<2.0.0)
Requires-Dist: elevate (>=0.1.3,<0.2.0)
Requires-Dist: gnista-library (==1.0.10)
Requires-Dist: structlog (>=21.1.0,<22.0.0)
Project-URL: Repository, https://gitlab.com/campfiresolutions/public/gnista.io-cli.git
